ergen/cli.py
ergen/main.py
ergen/template/erd.dot.jinja
ergen/types.py
ergen-0.1.0.dist-info/entry_points.txt
ergen-0.1.0.dist-info/LICENSE
ergen-0.1.0.dist-info/WHEEL
ergen-0.1.0.dist-info/METADATA
ergen-0.1.0.dist-info/RECORD
