Metadata-Version: 2.1
Name: ergen
Version: 0.1.0
Summary: 
License: Apache-2.0
Author: Naoya Yamashita
Author-email: conao3@gmail.com
Requires-Python: >=3.9,<4.0
Classifier: License :: OSI Approved :: Apache Software License
Classifier: Programming Language :: Python :: 3
Classifier: Programming Language :: Python :: 3.9
Requires-Dist: Jinja2 (>=3.0.2,<4.0.0)
Requires-Dist: PyYAML (>=6.0,<7.0)
Requires-Dist: pydantic (>=1.8.2,<2.0.0)
Requires-Dist: typer (>=0.4.0,<0.5.0)
